apibeat/__init__.py
apibeat/cli.py
apibeat/monitor.py
apibeat-0.1.8.dist-info/licenses/LICENSE
apibeat-0.1.8.dist-info/METADATA
apibeat-0.1.8.dist-info/WHEEL
apibeat-0.1.8.dist-info/entry_points.txt
apibeat-0.1.8.dist-info/top_level.txt
apibeat-0.1.8.dist-info/RECORD
